doover_scheduler.py
doover_scheduler-0.1.1.dist-info/METADATA
doover_scheduler-0.1.1.dist-info/WHEEL
doover_scheduler-0.1.1.dist-info/licenses/LICENSE
doover_scheduler-0.1.1.dist-info/RECORD
