Metadata-Version: 2.4
Name: doover-scheduler
Version: 0.1.1
Summary: Python package for managing Doover scheduled tasks.
Author-email: Doover Team <developers@doover.com>
License-File: LICENSE
Keywords: doover,doover-scheduler,scheduler
Classifier: Development Status :: 4 - Beta
Classifier: Intended Audience :: Developers
Classifier: Natural Language :: English
Classifier: Operating System :: OS Independent
Classifier: Programming Language :: Python
Requires-Python: >=3.11
Requires-Dist: pydoover>=0.4.10
